LICENSE
MANIFEST.in
README.md
requirements.txt
setup.py
test-requirements.txt
dockercloud/__init__.py
dockercloud/api/__init__.py
dockercloud/api/action.py
dockercloud/api/auth.py
dockercloud/api/base.py
dockercloud/api/container.py
dockercloud/api/events.py
dockercloud/api/exceptions.py
dockercloud/api/http.py
dockercloud/api/node.py
dockercloud/api/nodeaz.py
dockercloud/api/nodecluster.py
dockercloud/api/nodeprovider.py
dockercloud/api/noderegion.py
dockercloud/api/nodetype.py
dockercloud/api/repository.py
dockercloud/api/service.py
dockercloud/api/stack.py
dockercloud/api/tag.py
dockercloud/api/trigger.py
dockercloud/api/utils.py
python_dockercloud.egg-info/PKG-INFO
python_dockercloud.egg-info/SOURCES.txt
python_dockercloud.egg-info/dependency_links.txt
python_dockercloud.egg-info/requires.txt
python_dockercloud.egg-info/top_level.txt
tests/__init__.py
tests/fake_api.py
tests/test_action.py
tests/test_auth.py
tests/test_base.py
tests/test_container.py
tests/test_http.py
tests/test_http_reconnection.py
tests/test_node.py
tests/test_nodecluster.py
tests/test_nodeprovider.py
tests/test_noderegion.py
tests/test_nodetype.py
tests/test_repository.py
tests/test_service.py
tests/test_utils.py