Metadata-Version: 1.1
Name: python-dockercloud
Version: 1.0.10
Summary: Python Library for Dockercloud
Home-page: http://cloud.docker.com/
Author: Docker, Inc.
Author-email: info@docker.com
License: Apache v2
Keywords: docker cloud
Platform: UNKNOWN
Provides: docker
